trading212_rest/__init__.py
trading212_rest-0.5.0.dist-info/LICENSE
trading212_rest-0.5.0.dist-info/METADATA
trading212_rest-0.5.0.dist-info/WHEEL
trading212_rest-0.5.0.dist-info/top_level.txt
trading212_rest-0.5.0.dist-info/RECORD
